dimo/__init__.py
dimo/constants.py
dimo/dimo.py
dimo/environments.py
dimo/errors.py
dimo/eth_signer.py
dimo/request.py
dimo/api/__init__.py
dimo/api/auth.py
dimo/api/device_data.py
dimo/api/device_definitions.py
dimo/api/devices.py
dimo/api/events.py
dimo/api/token_exchange.py
dimo/api/trips.py
dimo/api/user.py
dimo/api/valuations.py
dimo/api/vehicle_signal_decoding.py
dimo/graphql/__init__.py
dimo/graphql/identity.py
dimo/graphql/telemetry.py
ha_dimo_python_sdk-0.0.8.dist-info/LICENSE
ha_dimo_python_sdk-0.0.8.dist-info/METADATA
ha_dimo_python_sdk-0.0.8.dist-info/WHEEL
ha_dimo_python_sdk-0.0.8.dist-info/top_level.txt
ha_dimo_python_sdk-0.0.8.dist-info/RECORD
