Metadata-Version: 2.1
Name: ha-dimo-python-sdk
Version: 0.0.8
Summary: DIMO SDK in Python
Author-email: Barrett Kowalsky <barrettkowalsky@gmail.com>
Project-URL: Homepage, https://github.com/DIMO-Network/dimo-python-sdk
Project-URL: Issues, https://github.com/DIMO-Network/dimo-python-sdk/issues
Keywords: dimo,sdk,python,depin,web3
Classifier: Programming Language :: Python :: 3
Classifier: License :: OSI Approved :: Apache Software License
Classifier: Operating System :: OS Independent
Requires-Python: >=3.8
License-File: LICENSE
Requires-Dist: requests>=2.30.0
Requires-Dist: ha-eth-account==0.1.4
